fileformats/audio.py
fileformats/model.py
fileformats/py.typed
fileformats/video.py
fileformats/application/__init__.py
fileformats/application/archive.py
fileformats/application/document.py
fileformats/application/medical.py
fileformats/application/misc.py
fileformats/application/presentation.py
fileformats/application/py.typed
fileformats/application/serialization.py
fileformats/application/spreadsheet.py
fileformats/core/__init__.py
fileformats/core/_version.py
fileformats/core/classifier.py
fileformats/core/collection.py
fileformats/core/converter_helpers.py
fileformats/core/datatype.py
fileformats/core/decorators.py
fileformats/core/exceptions.py
fileformats/core/extras.py
fileformats/core/field.py
fileformats/core/fileset.py
fileformats/core/fs_mount_identifier.py
fileformats/core/identification.py
fileformats/core/io.py
fileformats/core/mixin.py
fileformats/core/mock.py
fileformats/core/py.typed
fileformats/core/sampling.py
fileformats/core/typing.py
fileformats/core/utils.py
fileformats/field/__init__.py
fileformats/field/py.typed
fileformats/generic/__init__.py
fileformats/generic/directory.py
fileformats/generic/file.py
fileformats/generic/fsobject.py
fileformats/generic/generate_sample_data.py
fileformats/generic/py.typed
fileformats/generic/set.py
fileformats/image/__init__.py
fileformats/image/base.py
fileformats/image/notclassifiedyet.py
fileformats/image/py.typed
fileformats/image/raster.py
fileformats/image/vector.py
fileformats/testing/__init__.py
fileformats/testing/abstract.py
fileformats/testing/basic.py
fileformats/testing/headers.py
fileformats/testing/magic.py
fileformats/testing/py.typed
fileformats/testing/classifiers/file.py
fileformats/testing/classifiers/generic.py
fileformats/text/__init__.py
fileformats/text/ascii.py
fileformats/text/base.py
fileformats/text/unicode.py
fileformats/vendor/ms_excel/application.py
fileformats/vendor/ms_powerpoint/application.py
fileformats/vendor/ms_word/application.py
fileformats-0.17.3.dist-info/METADATA
fileformats-0.17.3.dist-info/WHEEL
fileformats-0.17.3.dist-info/licenses/AUTHORS
fileformats-0.17.3.dist-info/licenses/LICENSE
fileformats-0.17.3.dist-info/RECORD
