Metadata-Version: 2.4
Name: fileformats
Version: 0.17.3
Summary: Classes for representing different file formats in Python classes for use in type hinting in data workflows
Project-URL: repository, https://github.com/ArcanaFramework/fileformats
Author-email: "Thomas G. Close" <tom.g.close@gmail.com>
Maintainer-email: "Thomas G. Close" <tom.g.close@gmail.com>
License: Creative Commons Attribution 4.0 International Public License
License-File: AUTHORS
License-File: LICENSE
Keywords: MIME,data,file extension,file-formats,filetype,magic numbers
Classifier: Development Status :: 4 - Beta
Classifier: Environment :: Console
Classifier: Intended Audience :: Science/Research
Classifier: License :: OSI Approved :: Apache Software License
Classifier: Operating System :: MacOS :: MacOS X
Classifier: Operating System :: Microsoft :: Windows
Classifier: Operating System :: POSIX :: Linux
Classifier: Programming Language :: Python :: 3.8
Classifier: Programming Language :: Python :: 3.9
Classifier: Programming Language :: Python :: 3.10
Classifier: Programming Language :: Python :: 3.11
Classifier: Programming Language :: Python :: 3.12
Classifier: Programming Language :: Python :: 3.13
Classifier: Topic :: Scientific/Engineering
Requires-Python: >=3.8
Requires-Dist: typing-extensions>=4.6.3; python_version < '3.11'
Provides-Extra: dev
Requires-Dist: black; extra == 'dev'
Requires-Dist: codespell; extra == 'dev'
Requires-Dist: fileformats-extras[application,audio,image,model,text,vendor-openxmlformats-officedocument,video]; extra == 'dev'
Requires-Dist: flake8; extra == 'dev'
Requires-Dist: flake8-pyproject; extra == 'dev'
Requires-Dist: mypy>=1.5.1; extra == 'dev'
Requires-Dist: pre-commit; extra == 'dev'
Requires-Dist: pydata-sphinx-theme>=0.13; extra == 'dev'
Requires-Dist: pydicom; extra == 'dev'
Requires-Dist: pydra>=1.0a; extra == 'dev'
Requires-Dist: pytest-cov>=2.12.1; extra == 'dev'
Requires-Dist: pytest-env>=0.6.2; extra == 'dev'
Requires-Dist: pytest>=6.2.5; extra == 'dev'
Provides-Extra: docs
Requires-Dist: docutils>=0.10; extra == 'docs'
Requires-Dist: furo>=2022.2.14.1; extra == 'docs'
Requires-Dist: mock>1.0; extra == 'docs'
Requires-Dist: numpydoc>=0.6.0; extra == 'docs'
Requires-Dist: packaging; extra == 'docs'
Requires-Dist: sphinx-argparse>=0.2.0; extra == 'docs'
Requires-Dist: sphinx-click>=3.1; extra == 'docs'
Requires-Dist: sphinx>=2.1.2; extra == 'docs'
Provides-Extra: test
Requires-Dist: fileformats-extras[application,audio,image,model,text,vendor-openxmlformats-officedocument,video]; extra == 'test'
Requires-Dist: mypy>=1.5.1; extra == 'test'
Requires-Dist: pydra>=1.0a; extra == 'test'
Requires-Dist: pytest-cov>=2.12.1; extra == 'test'
Requires-Dist: pytest-env>=0.6.2; extra == 'test'
Requires-Dist: pytest>=6.2.5; extra == 'test'
